pamda/And.py
pamda/__.py
pamda/__init__.py
pamda/add.py
pamda/adjust.py
pamda/all.py
pamda/always.py
pamda/any.py
pamda/append.py
pamda/comparator.py
pamda/compose.py
pamda/concat.py
pamda/countBy.py
pamda/curry.py
pamda/curryN.py
pamda/difference.py
pamda/differenceWith.py
pamda/divide.py
pamda/equals.py
pamda/filter.py
pamda/find.py
pamda/identity.py
pamda/into.py
pamda/keys.py
pamda/map.py
pamda/multiply.py
pamda/nth.py
pamda/objOf.py
pamda/pipe.py
pamda/prop.py
pamda/reduce.py
pamda/reduceBy.py
pamda/reduced.py
pamda/reject.py
pamda/reverse.py
pamda/slice.py
pamda/sort.py
pamda/tail.py
pamda/private/__init__.py
pamda/private/_arity.py
pamda/private/_arrayReduce.py
pamda/private/_clone.py
pamda/private/_complement.py
pamda/private/_concat.py
pamda/private/_createReduce.py
pamda/private/_curry1.py
pamda/private/_curry2.py
pamda/private/_curry3.py
pamda/private/_curryN.py
pamda/private/_dispatchable.py
pamda/private/_equals.py
pamda/private/_filter.py
pamda/private/_has.py
pamda/private/_helper.py
pamda/private/_identity.py
pamda/private/_includesWith.py
pamda/private/_isArray.py
pamda/private/_isArrayLike.py
pamda/private/_isFunction.py
pamda/private/_isInteger.py
pamda/private/_isPlaceholder.py
pamda/private/_isString.py
pamda/private/_isTransformer.py
pamda/private/_map.py
pamda/private/_pipe.py
pamda/private/_reduce.py
pamda/private/_reduced.py
pamda/private/_stepCat.py
pamda/private/_xArrayReduce.py
pamda/private/_xReduce.py
pamda/private/_xReduceBy.py
pamda/private/_xall.py
pamda/private/_xany.py
pamda/private/_xfBase.py
pamda/private/_xfilter.py
pamda/private/_xfind.py
pamda/private/_xmap.py
pamda/private/_xwrap.py
test/__init__.py
test/test_And.py
test/test_add.py
test/test_adjust.py
test/test_all.py
test/test_always.py
test/test_any.py
test/test_append.py
test/test_comparator.py
test/test_compose.py
test/test_concat.py
test/test_countBy.py
test/test_curry.py
test/test_curryN.py
test/test_difference.py
test/test_differenceWith.py
test/test_divide.py
zydmayday_pamda-0.0.9.dist-info/LICENSE
zydmayday_pamda-0.0.9.dist-info/METADATA
zydmayday_pamda-0.0.9.dist-info/WHEEL
zydmayday_pamda-0.0.9.dist-info/top_level.txt
zydmayday_pamda-0.0.9.dist-info/RECORD
