Metadata-Version: 2.1
Name: zydmayday-pamda
Version: 0.0.9
Summary: A small clone of ramda
Home-page: https://github.com/zydmayday/pamda
Author-email: zydmayday@gmail.com
License: UNKNOWN
Keywords: functional programming,ramda
Platform: UNKNOWN
Classifier: License :: OSI Approved :: MIT License
Classifier: Intended Audience :: Developers
Classifier: Programming Language :: Python :: 3.9
License-File: LICENSE
